onediffusion/__about__.py
onediffusion/__init__.py
onediffusion/_configuration.py
onediffusion/_package.py
onediffusion/_sd.py
onediffusion/_types.py
onediffusion/cli.py
onediffusion/exceptions.py
onediffusion/models/__init__.py
onediffusion/models/auto/__init__.py
onediffusion/models/auto/configuration_auto.py
onediffusion/models/auto/factory.py
onediffusion/models/auto/modeling_auto.py
onediffusion/models/auto/modeling_flax_auto.py
onediffusion/models/auto/modeling_tf_auto.py
onediffusion/models/stable_diffusion/__init__.py
onediffusion/models/stable_diffusion/configuration_stable_diffusion.py
onediffusion/models/stable_diffusion/modeling_stable_diffusion.py
onediffusion/models/stable_diffusion/service.py
onediffusion/models/stable_diffusion_xl/__init__.py
onediffusion/models/stable_diffusion_xl/configuration_stable_diffusion_xl.py
onediffusion/models/stable_diffusion_xl/modeling_stable_diffusion_xl.py
onediffusion/models/stable_diffusion_xl/service.py
onediffusion/utils/__init__.py
onediffusion/utils/analytics.py
onediffusion/utils/codegen.py
onediffusion/utils/dantic.py
onediffusion/utils/import_utils.py
onediffusion/utils/lazy.py
onediffusion-0.0.3.dist-info/METADATA
onediffusion-0.0.3.dist-info/WHEEL
onediffusion-0.0.3.dist-info/entry_points.txt
onediffusion-0.0.3.dist-info/licenses/LICENSE
onediffusion-0.0.3.dist-info/RECORD
