Metadata-Version: 2.1
Name: onediffusion
Version: 0.0.3
Summary: Onediffusion: REST API server for running any diffusion models - Stable Diffusion, Anything, ControlNet, Lora, Custom
Project-URL: Chat, https://l.bentoml.com/join-openllm-discord
Project-URL: Documentation, https://github.com/BentoML/OneDiffusion#readme
Project-URL: Issues, https://github.com/BentoML/OneDiffusion/issues
Project-URL: Source, https://github.com/BentoML/OneDiffusion
Author-email: Shenyang Zhao <larme@bentoml.com>, BentoML Team <contact@bentoml.com>
License-Expression: Apache-2.0
License-File: LICENSE
Keywords: AI,BentoML,Diffusers,Generative AI,Lora,MLOps,Model Deployment,Model Serving,PyTorch,Stable Diffusion
Classifier: Development Status :: 4 - Beta
Classifier: License :: OSI Approved :: Apache Software License
Classifier: Operating System :: OS Independent
Classifier: Programming Language :: Python
Classifier: Programming Language :: Python :: 3
Classifier: Programming Language :: Python :: 3 :: Only
Classifier: Programming Language :: Python :: 3.8
Classifier: Programming Language :: Python :: 3.9
Classifier: Programming Language :: Python :: 3.10
Classifier: Programming Language :: Python :: 3.11
Classifier: Programming Language :: Python :: Implementation :: CPython
Classifier: Programming Language :: Python :: Implementation :: PyPy
Classifier: Topic :: Scientific/Engineering :: Artificial Intelligence
Classifier: Topic :: Software Development :: Libraries
Requires-Python: >=3.8
Requires-Dist: accelerate
Requires-Dist: attrs>=23.1.0
Requires-Dist: bentoml[io]>=1.1.2
Requires-Dist: cattrs>=23.1.0
Requires-Dist: diffusers[torch]>=0.19.3
Requires-Dist: huggingface-hub
Requires-Dist: inflection
Requires-Dist: orjson
Requires-Dist: pydantic
Requires-Dist: safetensors
Requires-Dist: tabulate[widechars]>=0.9.0
Requires-Dist: transformers
